<?xml version="1.0" encoding="UTF-8"?><tool name="Gladius" category="SWORD"><bodies><body id="0"><layers><layer id="0" name="Layer0"><vertices><v x="397.70728" y="195.58727"/><v x="399.66037" y="196.65823"/><v x="400.61096" y="198.67268"/><v x="400.19595" y="200.86115"/><v x="398.57385" y="202.3877"/><v x="395.925" y="202.41975"/><v x="394.41116" y="201.5983"/><v x="393.46057" y="199.58385"/><v x="393.87558" y="197.39539"/><v x="395.49768" y="195.86884"/></vertices><outline><v x="397.70728" y="195.58727"/><v x="399.66037" y="196.65823"/><v x="400.61096" y="198.67268"/><v x="400.19595" y="200.86115"/><v x="398.57385" y="202.3877"/><v x="395.925" y="202.41975"/><v x="394.41116" y="201.5983"/><v x="393.46057" y="199.58385"/><v x="393.87558" y="197.39539"/><v x="395.49768" y="195.86884"/></outline><refVertices><v x="397.03577" y="199.12827"/></refVertices><properties chemicalEnergy="400.0" combustible="true" density="3.2" flameTemperature="700.0" flammability="0.0" flammable="false" friction="0.4" hardness="3.0" heatResistance="0.6" ignitionTemperature="600.0" juiceColor="-5369829" juiceFlammability="0.0" juiceIndex="0" juicinessDensity="0.0" juicinessLowerPressure="0.0" juicinessUpperPressure="0.0" juicy="false" materialNumber="17" order="0" restitution="0.35" sharpness="0.0" tenacity="4.0" colorSquareId="-1" defaultColor="-8765145"/><decorations/></layer><layer id="1" name="Layer1"><vertices><v x="395.78412" y="202.29425"/><v x="394.50412" y="203.72885"/><v x="395.65823" y="205.03616"/><v x="398.60623" y="204.6118"/><v x="399.46274" y="203.51103"/><v x="398.54025" y="202.4135"/></vertices><outline><v x="395.78412" y="202.29425"/><v x="398.54025" y="202.4135"/><v x="399.46274" y="203.51103"/><v x="398.60623" y="204.6118"/><v x="395.65823" y="205.03616"/><v x="394.50412" y="203.72885"/></outline><refVertices/><properties chemicalEnergy="400.0" combustible="true" density="3.2" flameTemperature="700.0" flammability="0.0" flammable="false" friction="0.4" hardness="3.0" heatResistance="0.6" ignitionTemperature="600.0" juiceColor="-5369829" juiceFlammability="0.0" juiceIndex="0" juicinessDensity="0.0" juicinessLowerPressure="0.0" juicinessUpperPressure="0.0" juicy="false" materialNumber="17" order="0" restitution="0.35" sharpness="0.0" tenacity="4.0" colorSquareId="-1" defaultColor="-2051712"/><decorations/></layer><layer id="2" name="Layer2"><vertices><v x="395.63434" y="204.86607"/><v x="394.79898" y="206.12807"/><v x="395.8947" y="207.46762"/><v x="398.58444" y="207.20085"/><v x="399.55637" y="206.10696"/><v x="398.59616" y="204.46266"/></vertices><outline><v x="398.59616" y="204.46266"/><v x="399.55637" y="206.10696"/><v x="398.58444" y="207.20085"/><v x="395.8947" y="207.46762"/><v x="394.79898" y="206.12807"/><v x="395.63434" y="204.86607"/></outline><refVertices/><properties chemicalEnergy="400.0" combustible="true" density="3.2" flameTemperature="700.0" flammability="0.0" flammable="false" friction="0.4" hardness="3.0" heatResistance="0.6" ignitionTemperature="600.0" juiceColor="-5369829" juiceFlammability="0.0" juiceIndex="0" juicinessDensity="0.0" juicinessLowerPressure="0.0" juicinessUpperPressure="0.0" juicy="false" materialNumber="17" order="0" restitution="0.35" sharpness="0.0" tenacity="4.0" colorSquareId="-1" defaultColor="-2051712"/><decorations/></layer><layer id="3" name="Layer3"><vertices><v x="395.88147" y="207.30872"/><v x="395.02374" y="208.78952"/><v x="395.84433" y="210.05693"/><v x="398.67944" y="210.1144"/><v x="399.3593" y="208.7347"/><v x="398.4749" y="206.97615"/></vertices><outline><v x="398.4749" y="206.97615"/><v x="399.3593" y="208.7347"/><v x="398.67944" y="210.1144"/><v x="395.84433" y="210.05693"/><v x="395.02374" y="208.78952"/><v x="395.88147" y="207.30872"/></outline><refVertices/><properties chemicalEnergy="500.0" combustible="true" density="2.4" flameTemperature="700.0" flammability="0.0" flammable="false" friction="0.4" hardness="2.0" heatResistance="0.6" ignitionTemperature="500.0" juiceColor="-5369829" juiceFlammability="0.0" juiceIndex="0" juicinessDensity="0.0" juicinessLowerPressure="0.0" juicinessUpperPressure="0.0" juicy="false" materialNumber="0" order="0" restitution="0.35" sharpness="0.0" tenacity="4.0" colorSquareId="-1" defaultColor="-2051712"/><decorations/></layer><layer id="4" name="Layer4"><vertices><v x="395.86792" y="209.81583"/><v x="395.2213" y="210.98279"/><v x="395.23596" y="212.8032"/><v x="399.3358" y="212.79517"/><v x="399.28366" y="211.077"/><v x="398.611" y="209.90674"/></vertices><outline><v x="395.86792" y="209.81583"/><v x="398.611" y="209.90674"/><v x="399.28366" y="211.077"/><v x="399.3358" y="212.79517"/><v x="395.23596" y="212.8032"/><v x="395.2213" y="210.98279"/></outline><refVertices/><properties chemicalEnergy="500.0" combustible="true" density="2.4" flameTemperature="700.0" flammability="0.0" flammable="false" friction="0.4" hardness="2.0" heatResistance="0.6" ignitionTemperature="500.0" juiceColor="-5369829" juiceFlammability="0.0" juiceIndex="0" juicinessDensity="0.0" juicinessLowerPressure="0.0" juicinessUpperPressure="0.0" juicy="false" materialNumber="0" order="0" restitution="0.35" sharpness="0.0" tenacity="4.0" colorSquareId="-1" defaultColor="-2051712"/><decorations/></layer><layer id="6" name="Layer6"><vertices><v x="392.98972" y="217.26108"/><v x="401.59613" y="217.41841"/><v x="400.92026" y="227.29887"/><v x="393.91144" y="227.43991"/></vertices><outline><v x="392.98972" y="217.26108"/><v x="401.59613" y="217.41841"/><v x="400.92026" y="227.29887"/><v x="393.91144" y="227.43991"/></outline><refVertices/><properties chemicalEnergy="0.0" combustible="false" density="31.4" flameTemperature="0.0" flammability="0.0" flammable="false" friction="0.4" hardness="7.0" heatResistance="0.9" ignitionTemperature="0.0" juiceColor="-5369829" juiceFlammability="0.0" juiceIndex="0" juicinessDensity="0.0" juicinessLowerPressure="0.0" juicinessUpperPressure="0.0" juicy="false" materialNumber="1" order="0" restitution="0.25" sharpness="0.6" tenacity="7.0" colorSquareId="-1" defaultColor="-5066062"/><decorations/></layer><layer id="5" name="Layer5"><vertices><v x="391.48407" y="217.70854"/><v x="403.4855" y="217.69093"/><v x="403.4834" y="214.91699"/><v x="401.4448" y="213.1519"/><v x="399.273" y="212.2149"/><v x="395.4778" y="212.23877"/><v x="392.74948" y="213.32788"/><v x="391.41565" y="214.82135"/></vertices><outline><v x="399.273" y="212.2149"/><v x="401.4448" y="213.1519"/><v x="403.4834" y="214.91699"/><v x="403.4855" y="217.69093"/><v x="391.48407" y="217.70854"/><v x="391.41565" y="214.82135"/><v x="392.74948" y="213.32788"/><v x="395.4778" y="212.23877"/></outline><refVertices/><properties chemicalEnergy="400.0" combustible="true" density="3.2" flameTemperature="700.0" flammability="0.0" flammable="false" friction="0.4" hardness="3.0" heatResistance="0.6" ignitionTemperature="600.0" juiceColor="-5369829" juiceFlammability="0.0" juiceIndex="0" juicinessDensity="0.0" juicinessLowerPressure="0.0" juicinessUpperPressure="0.0" juicy="false" materialNumber="17" order="0" restitution="0.35" sharpness="0.0" tenacity="4.0" colorSquareId="-1" defaultColor="-10082029"/><decorations/></layer><layer id="7" name="Layer7"><vertices><v x="393.9006" y="226.92775"/><v x="400.92166" y="226.82338"/><v x="401.10873" y="245.2181"/><v x="393.644" y="245.20166"/></vertices><outline><v x="400.92166" y="226.82338"/><v x="401.10873" y="245.2181"/><v x="393.644" y="245.20166"/><v x="393.9006" y="226.92775"/></outline><refVertices/><properties chemicalEnergy="0.0" combustible="false" density="31.4" flameTemperature="0.0" flammability="0.0" flammable="false" friction="0.4" hardness="7.0" heatResistance="0.9" ignitionTemperature="0.0" juiceColor="-5369829" juiceFlammability="0.0" juiceIndex="0" juicinessDensity="0.0" juicinessLowerPressure="0.0" juicinessUpperPressure="0.0" juicy="false" materialNumber="1" order="0" restitution="0.25" sharpness="0.6" tenacity="7.0" colorSquareId="-1" defaultColor="-5066062"/><decorations/></layer><layer id="8" name="Layer8"><vertices><v x="401.10574" y="244.99883"/><v x="393.67474" y="244.95808"/><v x="393.2019" y="256.9845"/><v x="401.74295" y="257.07248"/></vertices><outline><v x="393.67474" y="244.95808"/><v x="401.10574" y="244.99883"/><v x="401.74295" y="257.07248"/><v x="393.2019" y="256.9845"/></outline><refVertices/><properties chemicalEnergy="0.0" combustible="false" density="31.4" flameTemperature="0.0" flammability="0.0" flammable="false" friction="0.4" hardness="7.0" heatResistance="0.9" ignitionTemperature="0.0" juiceColor="-5369829" juiceFlammability="0.0" juiceIndex="0" juicinessDensity="0.0" juicinessLowerPressure="0.0" juicinessUpperPressure="0.0" juicy="false" materialNumber="1" order="0" restitution="0.25" sharpness="0.6" tenacity="7.0" colorSquareId="-1" defaultColor="-5066062"/><decorations/></layer><layer id="9" name="Layer9"><vertices><v x="393.25504" y="256.61688"/><v x="401.6922" y="256.58945"/><v x="401.74814" y="264.40704"/><v x="401.31412" y="269.33298"/><v x="393.8308" y="269.78424"/><v x="393.2812" y="264.39816"/><v x="394.3947" y="273.25238"/><v x="395.5702" y="277.98956"/><v x="399.43967" y="278.00995"/><v x="400.64612" y="273.0523"/><v x="397.58435" y="283.50046"/></vertices><outline><v x="401.6922" y="256.58945"/><v x="401.74814" y="264.40704"/><v x="401.31412" y="269.33298"/><v x="400.64612" y="273.0523"/><v x="399.43967" y="278.00995"/><v x="397.58435" y="283.50046"/><v x="395.5702" y="277.98956"/><v x="394.3947" y="273.25238"/><v x="393.8308" y="269.78424"/><v x="393.2812" y="264.39816"/><v x="393.25504" y="256.61688"/></outline><refVertices/><properties chemicalEnergy="0.0" combustible="false" density="31.4" flameTemperature="0.0" flammability="0.0" flammable="false" friction="0.4" hardness="7.0" heatResistance="0.9" ignitionTemperature="0.0" juiceColor="-5369829" juiceFlammability="0.0" juiceIndex="0" juicinessDensity="0.0" juicinessLowerPressure="0.0" juicinessUpperPressure="0.0" juicy="false" materialNumber="1" order="0" restitution="0.25" sharpness="0.7" tenacity="7.0" colorSquareId="-1" defaultColor="-5066062"/><decorations/></layer></layers><projectiles/><fireSourceList/><liquidSourceList/><ammoList/><bombList/><dragList/><usageList><usage type="Stabbing"><properties/></usage><usage type="Slashing"><properties/></usage></usageList></body></bodies><joints/><panelColors/></tool>