<?xml version="1.0" encoding="UTF-8"?><tool name="My Petrol Container" category="OTHER"><bodies><body id="0"><layers><layer id="0" name="Layer0"><vertices><v x="366.4744" y="241.34863"/><v x="366.30347" y="233.20941"/><v x="368.12326" y="196.42758"/><v x="371.3979" y="190.42264"/><v x="377.4181" y="188.58733"/><v x="424.8749" y="189.74042"/><v x="429.6532" y="194.24524"/><v x="431.6405" y="201.37817"/><v x="433.38458" y="260.89444"/><v x="424.00775" y="274.68167"/><v x="392.99854" y="275.79193"/><v x="369.81757" y="247.57494"/></vertices><outline><v x="377.4181" y="188.58733"/><v x="424.8749" y="189.74042"/><v x="429.6532" y="194.24524"/><v x="431.6405" y="201.37817"/><v x="433.38458" y="260.89444"/><v x="424.00775" y="274.68167"/><v x="392.99854" y="275.79193"/><v x="369.81757" y="247.57494"/><v x="366.4744" y="241.34863"/><v x="366.30347" y="233.20941"/><v x="368.12326" y="196.42758"/><v x="371.3979" y="190.42264"/></outline><refVertices/><properties chemicalEnergy="2000.0" combustible="false" density="4.8" flameTemperature="800.0" flammability="0.0" flammable="true" friction="0.5" hardness="4.0" heatResistance="10.0" ignitionTemperature="600.0" juiceColor="-65536" juiceFlammability="0.0" juiceIndex="0" juicinessDensity="0.0" juicinessLowerPressure="0.0" juicinessUpperPressure="0.0" juicy="false" materialNumber="15" order="0" restitution="0.5" sharpness="0.0" tenacity="6.0" colorSquareId="0" defaultColor="-3529689"/><decorations/></layer><layer id="1" name="Layer1"><vertices><v x="369.38287" y="244.93243"/><v x="370.1623" y="268.1827"/><v x="380.74045" y="258.99878"/><v x="376.00806" y="265.87558"/></vertices><outline><v x="369.38287" y="244.93243"/><v x="380.74045" y="258.99878"/><v x="376.00806" y="265.87558"/><v x="370.1623" y="268.1827"/></outline><refVertices/><properties chemicalEnergy="2000.0" combustible="false" density="4.8" flameTemperature="800.0" flammability="0.0" flammable="true" friction="0.5" hardness="4.0" heatResistance="10.0" ignitionTemperature="600.0" juiceColor="-65536" juiceFlammability="0.0" juiceIndex="0" juicinessDensity="0.0" juicinessLowerPressure="0.0" juicinessUpperPressure="0.0" juicy="false" materialNumber="15" order="0" restitution="0.5" sharpness="0.0" tenacity="6.0" colorSquareId="0" defaultColor="-3529689"/><decorations/></layer><layer id="2" name="Layer2"><vertices><v x="375.48105" y="265.06976"/><v x="370.03992" y="267.25006"/><v x="377.52625" y="282.96753"/><v x="382.64096" y="279.59595"/><v x="373.57687" y="276.2442"/></vertices><outline><v x="375.48105" y="265.06976"/><v x="382.64096" y="279.59595"/><v x="377.52625" y="282.96753"/><v x="373.57687" y="276.2442"/><v x="370.03992" y="267.25006"/></outline><refVertices/><properties chemicalEnergy="2000.0" combustible="false" density="4.8" flameTemperature="800.0" flammability="0.0" flammable="true" friction="0.5" hardness="4.0" heatResistance="10.0" ignitionTemperature="600.0" juiceColor="-65536" juiceFlammability="0.0" juiceIndex="0" juicinessDensity="0.0" juicinessLowerPressure="0.0" juicinessUpperPressure="0.0" juicy="false" materialNumber="15" order="0" restitution="0.5" sharpness="0.0" tenacity="6.0" colorSquareId="0" defaultColor="-3529689"/><decorations/></layer><layer id="3" name="Layer3"><vertices><v x="380.98175" y="278.20386"/><v x="377.77863" y="283.00027"/><v x="389.469" y="284.38367"/><v x="380.88684" y="287.21527"/><v x="388.82532" y="291.83362"/></vertices><outline><v x="380.98175" y="278.20386"/><v x="389.469" y="284.38367"/><v x="388.82532" y="291.83362"/><v x="380.88684" y="287.21527"/><v x="377.77863" y="283.00027"/></outline><refVertices/><properties chemicalEnergy="2000.0" combustible="false" density="4.8" flameTemperature="800.0" flammability="0.0" flammable="true" friction="0.5" hardness="4.0" heatResistance="10.0" ignitionTemperature="600.0" juiceColor="-65536" juiceFlammability="0.0" juiceIndex="0" juicinessDensity="0.0" juicinessLowerPressure="0.0" juicinessUpperPressure="0.0" juicy="false" materialNumber="15" order="0" restitution="0.5" sharpness="0.0" tenacity="6.0" colorSquareId="0" defaultColor="-3529689"/><decorations/></layer><layer id="4" name="Layer4"><vertices><v x="388.1865" y="291.40002"/><v x="389.0998" y="284.64203"/><v x="412.87387" y="284.1402"/><v x="413.56982" y="289.31345"/></vertices><outline><v x="412.87387" y="284.1402"/><v x="413.56982" y="289.31345"/><v x="388.1865" y="291.40002"/><v x="389.0998" y="284.64203"/></outline><refVertices/><properties chemicalEnergy="2000.0" combustible="false" density="4.8" flameTemperature="800.0" flammability="0.0" flammable="true" friction="0.5" hardness="4.0" heatResistance="10.0" ignitionTemperature="600.0" juiceColor="-65536" juiceFlammability="0.0" juiceIndex="0" juicinessDensity="0.0" juicinessLowerPressure="0.0" juicinessUpperPressure="0.0" juicy="false" materialNumber="15" order="0" restitution="0.5" sharpness="0.0" tenacity="6.0" colorSquareId="0" defaultColor="-3529689"/><decorations/></layer><layer id="5" name="Layer5"><vertices><v x="413.52792" y="289.00122"/><v x="411.68106" y="285.09805"/><v x="424.18616" y="273.7787"/><v x="412.55197" y="275.00632"/><v x="416.17804" y="273.51587"/></vertices><outline><v x="416.17804" y="273.51587"/><v x="424.18616" y="273.7787"/><v x="413.52792" y="289.00122"/><v x="411.68106" y="285.09805"/><v x="412.55197" y="275.00632"/></outline><refVertices/><properties chemicalEnergy="2000.0" combustible="false" density="4.8" flameTemperature="800.0" flammability="0.0" flammable="true" friction="0.5" hardness="4.0" heatResistance="10.0" ignitionTemperature="600.0" juiceColor="-65536" juiceFlammability="0.0" juiceIndex="0" juicinessDensity="0.0" juicinessLowerPressure="0.0" juicinessUpperPressure="0.0" juicy="false" materialNumber="15" order="0" restitution="0.5" sharpness="0.0" tenacity="6.0" colorSquareId="0" defaultColor="-3529689"/><decorations/></layer><layer id="6" name="Layer6"><vertices><v x="419.54117" y="279.07422"/><v x="426.182" y="285.73444"/><v x="430.98788" y="277.82736"/><v x="424.95953" y="270.9477"/></vertices><outline><v x="424.95953" y="270.9477"/><v x="430.98788" y="277.82736"/><v x="426.182" y="285.73444"/><v x="419.54117" y="279.07422"/></outline><refVertices/><properties chemicalEnergy="2000.0" combustible="false" density="4.8" flameTemperature="800.0" flammability="0.0" flammable="true" friction="0.5" hardness="4.0" heatResistance="10.0" ignitionTemperature="600.0" juiceColor="-65536" juiceFlammability="0.0" juiceIndex="0" juicinessDensity="0.0" juicinessLowerPressure="0.0" juicinessUpperPressure="0.0" juicy="false" materialNumber="15" order="0" restitution="0.5" sharpness="0.0" tenacity="6.0" colorSquareId="0" defaultColor="-3529689"/><decorations/></layer></layers><projectiles/><fireSourceList/><liquidSourceList><liquidSource id="0" name="Liquid Source 0"><properties extent="7.61248" liquid="2" liquidSourceDirectionX="0.6104342" liquidSourceDirectionY="0.79206705" liquidSourceOriginX="433.1681" liquidSourceOriginY="273.20178" sealBodyId="1"/></liquidSource></liquidSourceList><ammoList/><bombList/><dragList/><usageList><usage type="Liquid Container"><properties quantity="0.0" liquidSources="0"/></usage></usageList></body><body id="1"><layers><layer id="0" name="Layer0"><vertices><v x="418.60825" y="281.51547"/><v x="427.66187" y="269.3694"/><v x="431.03702" y="273.31796"/><v x="421.7448" y="285.1977"/></vertices><outline><v x="427.66187" y="269.3694"/><v x="431.03702" y="273.31796"/><v x="421.7448" y="285.1977"/><v x="418.60825" y="281.51547"/></outline><refVertices/><properties chemicalEnergy="2000.0" combustible="false" density="4.8" flameTemperature="800.0" flammability="0.0" flammable="true" friction="0.5" hardness="4.0" heatResistance="10.0" ignitionTemperature="600.0" juiceColor="-65536" juiceFlammability="0.0" juiceIndex="0" juicinessDensity="0.0" juicinessLowerPressure="0.0" juicinessUpperPressure="0.0" juicy="false" materialNumber="15" order="0" restitution="0.5" sharpness="0.0" tenacity="6.0" colorSquareId="-1" defaultColor="-15660442"/><decorations/></layer><layer id="1" name="Layer1"><vertices><v x="421.28815" y="282.1401"/><v x="425.85217" y="286.92194"/><v x="432.78955" y="277.77338"/><v x="428.48395" y="273.10614"/></vertices><outline><v x="428.48395" y="273.10614"/><v x="432.78955" y="277.77338"/><v x="425.85217" y="286.92194"/><v x="421.28815" y="282.1401"/></outline><refVertices/><properties chemicalEnergy="6000.0" combustible="false" density="2.4" flameTemperature="2000.0" flammability="0.0" flammable="true" friction="0.4" hardness="2.0" heatResistance="10.0" ignitionTemperature="573.0" juiceColor="-65536" juiceFlammability="0.0" juiceIndex="0" juicinessDensity="0.0" juicinessLowerPressure="0.0" juicinessUpperPressure="0.0" juicy="false" materialNumber="0" order="0" restitution="0.35" sharpness="0.0" tenacity="4.0" colorSquareId="0" defaultColor="-15660442"/><decorations/></layer><layer id="2" name="Layer2"><vertices><v x="427.26413" y="282.4253"/><v x="429.91455" y="285.39575"/><v x="432.01648" y="281.64188"/><v x="429.47723" y="279.02625"/></vertices><outline><v x="429.47723" y="279.02625"/><v x="432.01648" y="281.64188"/><v x="429.91455" y="285.39575"/><v x="427.26413" y="282.4253"/></outline><refVertices/><properties chemicalEnergy="6000.0" combustible="false" density="2.4" flameTemperature="2000.0" flammability="0.0" flammable="true" friction="0.4" hardness="2.0" heatResistance="10.0" ignitionTemperature="573.0" juiceColor="-65536" juiceFlammability="0.0" juiceIndex="0" juicinessDensity="0.0" juicinessLowerPressure="0.0" juicinessUpperPressure="0.0" juicy="false" materialNumber="0" order="0" restitution="0.35" sharpness="0.0" tenacity="4.0" colorSquareId="0" defaultColor="-15660442"/><decorations/></layer></layers><projectiles/><fireSourceList/><liquidSourceList/><ammoList/><bombList/><dragList/><usageList/></body></bodies><joints><joint id="0" collideConnected="false" type="8" bodyAId="0" bodyBId="1" referenceAngle="0.0"><v x="423.03308" y="274.1693"/><v x="423.03308" y="274.1693"/></joint></joints><panelColors/></tool>